simplation/__init__.py
simplation/cli.py
simplation-3.0.3.dist-info/licenses/LICENSE
tests/__init__.py
simplation-3.0.3.dist-info/METADATA
simplation-3.0.3.dist-info/WHEEL
simplation-3.0.3.dist-info/entry_points.txt
simplation-3.0.3.dist-info/top_level.txt
simplation-3.0.3.dist-info/RECORD
