Metadata-Version: 2.4
Name: simplation
Version: 3.0.3
Summary: A powerful command-line tool for analyzing and visualizing simulation data from CSV files
Home-page: https://github.com/Gueni/simplation
Author: M. Gueni
Author-email: "M. Gueni" <mohamedgueni@outlook.com>
Project-URL: Homepage, https://github.com/Gueni/simplation
Project-URL: Bug Reports, https://github.com/Gueni/simplation/issues
Project-URL: Source, https://github.com/Gueni/simplation
Keywords: simulation,data-analysis,csv,engineering,visualization,statistics
Classifier: Development Status :: 4 - Beta
Classifier: Intended Audience :: Science/Research
Classifier: Intended Audience :: Education
Classifier: Topic :: Scientific/Engineering
Classifier: License :: OSI Approved :: MIT License
Classifier: Programming Language :: Python :: 3
Classifier: Programming Language :: Python :: 3.10
Classifier: Programming Language :: Python :: 3.11
Classifier: Programming Language :: Python :: 3.12
Classifier: Programming Language :: Python :: 3.13
Classifier: Operating System :: OS Independent
Requires-Python: >=3.10.8
License-File: LICENSE
Requires-Dist: colorama>=0.4.6
Requires-Dist: numpy>=1.22.4
Requires-Dist: pandas>=2.2.2
Requires-Dist: pyfiglet>=0.8.post1
Requires-Dist: rich>=14.0.0
Requires-Dist: matplotlib>=3.6.2
Provides-Extra: dev
Requires-Dist: pytest>=6.0; extra == "dev"
Requires-Dist: black>=22.0; extra == "dev"
Requires-Dist: flake8>=4.0; extra == "dev"
Requires-Dist: twine>=4.0; extra == "dev"
Dynamic: author
Dynamic: home-page
Dynamic: license-file
Dynamic: requires-python
